__init__.py
candlestick_patterns/__init__.py
candlestick_patterns/pattern_detector.py
candlestick_patterns/bearish_patterns/__init__.py
candlestick_patterns/bearish_patterns/bearish_engulfing_pattern.py
candlestick_patterns/bearish_patterns/dark_cloud_cover_pattern.py
candlestick_patterns/bearish_patterns/evening_star_pattern.py
candlestick_patterns/bullish_patterns/__init__.py
candlestick_patterns/bullish_patterns/bullish_engulfing_pattern.py
candlestick_patterns/bullish_patterns/hammer_pattern.py
candlestick_patterns/bullish_patterns/morning_star_pattern.py
candlestick_patterns/candlesticks/__init__.py
candlestick_patterns/candlesticks/candlesticks.py
candlestick_patterns/utils/constants.py
candlestick_patterns-1.2.0.dist-info/LICENSE
candlestick_patterns-1.2.0.dist-info/METADATA
candlestick_patterns-1.2.0.dist-info/WHEEL
candlestick_patterns-1.2.0.dist-info/top_level.txt
candlestick_patterns-1.2.0.dist-info/RECORD
