Metadata-Version: 2.1
Name: candlestick_patterns
Version: 1.2.0
Classifier: Programming Language :: Python :: 3
Classifier: License :: OSI Approved :: MIT License
Classifier: Operating System :: OS Independent
Requires-Python: >=3.10
License-File: LICENSE
Requires-Dist: aiohttp==3.9.1
Requires-Dist: aiosignal==1.3.1
Requires-Dist: annotated-types==0.6.0
Requires-Dist: attrs==23.1.0
Requires-Dist: black==23.12.0
Requires-Dist: build==1.0.3
Requires-Dist: certifi==2023.11.17
Requires-Dist: charset-normalizer==3.3.2
Requires-Dist: click==8.1.7
Requires-Dist: docutils==0.20.1
Requires-Dist: frozenlist==1.4.1
Requires-Dist: idna==3.6
Requires-Dist: importlib-metadata==7.0.0
Requires-Dist: isort==5.13.2
Requires-Dist: jaraco.classes==3.3.0
Requires-Dist: keyring==24.3.0
Requires-Dist: markdown-it-py==3.0.0
Requires-Dist: mdurl==0.1.2
Requires-Dist: more-itertools==10.1.0
Requires-Dist: multidict==6.0.4
Requires-Dist: mypy==1.7.1
Requires-Dist: mypy-extensions==1.0.0
Requires-Dist: nh3==0.2.15
Requires-Dist: packaging==23.2
Requires-Dist: pathspec==0.12.1
Requires-Dist: pkginfo==1.9.6
Requires-Dist: platformdirs==4.1.0
Requires-Dist: polygon-api-client==1.13.3
Requires-Dist: pydantic==2.5.2
Requires-Dist: pydantic_core==2.14.5
Requires-Dist: Pygments==2.17.2
Requires-Dist: pyproject_hooks==1.0.0
Requires-Dist: readme-renderer==42.0
Requires-Dist: requests==2.31.0
Requires-Dist: requests-toolbelt==1.0.0
Requires-Dist: rfc3986==2.0.0
Requires-Dist: rich==13.7.0
Requires-Dist: setuptools==69.0.2
Requires-Dist: twine==4.0.2
Requires-Dist: typing_extensions==4.9.0
Requires-Dist: urllib3==1.26.18
Requires-Dist: websockets==12.0
Requires-Dist: wheel==0.42.0
Requires-Dist: yarl==1.9.4
Requires-Dist: zipp==3.17.0
